Examples/__init__.py
Examples/quick_start.py
Examples/test_check_examples.py
Examples/VirtualLab/__init__.py
Examples/VirtualLab/make_speckle_images.py
Examples/VirtualLab/virtual_experiment_f.py
Examples/VirtualLab/virtual_experiment_u.py
Examples/VirtualLab/virtual_sensitivity_rigid_body.py
muDIC/__init__.py
muDIC/IO/__init__.py
muDIC/IO/image_stack.py
muDIC/IO/readWriteUtils.py
muDIC/elements/__init__.py
muDIC/elements/b_splines.py
muDIC/elements/fieldInterpolator.py
muDIC/elements/q4.py
muDIC/filtering/__init__.py
muDIC/filtering/filters.py
muDIC/mesh/__init__.py
muDIC/mesh/meshUtilities.py
muDIC/mesh/mesh_translator.py
muDIC/post/__init__.py
muDIC/post/viz.py
muDIC/solver/__init__.py
muDIC/solver/correlate.py
muDIC/solver/custom_exceptions.py
muDIC/solver/reference.py
muDIC/solver/reference_q4.py
muDIC/tests/__init__.py
muDIC/tests/test_dic/__init__.py
muDIC/tests/test_dic/test_DIC_Post.py
muDIC/tests/test_dic/test_DIC_core.py
muDIC/tests/test_dic/test_imageReader.py
muDIC/tests/test_vlab/__init__.py
muDIC/tests/test_vlab/test_downsample.py
muDIC/tests/test_vlab/test_imageDeformer.py
muDIC/tests/test_vlab/test_virtualTensileTest.py
muDIC/utils/__init__.py
muDIC/utils/utilities.py
muDIC/vlab/__init__.py
muDIC/vlab/deformation_fields.py
muDIC/vlab/downsampler.py
muDIC/vlab/image_deformer.py
muDIC/vlab/noise.py
muDIC/vlab/speckle.py
muDIC/vlab/syntheticImageGenerator.py
muDIC-0.2.1.dist-info/LICENSE
muDIC-0.2.1.dist-info/METADATA
muDIC-0.2.1.dist-info/WHEEL
muDIC-0.2.1.dist-info/top_level.txt
muDIC-0.2.1.dist-info/RECORD
