Metadata-Version: 2.1
Name: muDIC
Version: 0.2.1
Summary: A digital image correlation toolkit
Home-page: https://github.com/PolymerGuy/muDIC
Author: PolymerGuy
Author-email: sindre.n.olufsen@ntnu.no
License: UNKNOWN
Platform: UNKNOWN
Classifier: Programming Language :: Python :: 3
Classifier: License :: OSI Approved :: MIT License
Classifier: Operating System :: OS Independent
Requires-Dist: numba
Requires-Dist: scipy
Requires-Dist: matplotlib
Requires-Dist: numpy
Requires-Dist: Pillow
Requires-Dist: dill
Requires-Dist: nose
Requires-Dist: scikit-image
Requires-Dist: muDIC
Requires-Dist: natsort
